README.md
setup.py
pulumi_lidarr/__init__.py
pulumi_lidarr/_utilities.py
pulumi_lidarr/provider.py
pulumi_lidarr/pulumi-plugin.json
pulumi_lidarr/py.typed
pulumi_lidarr.egg-info/PKG-INFO
pulumi_lidarr.egg-info/SOURCES.txt
pulumi_lidarr.egg-info/dependency_links.txt
pulumi_lidarr.egg-info/not-zip-safe
pulumi_lidarr.egg-info/requires.txt
pulumi_lidarr.egg-info/top_level.txt
pulumi_lidarr/artists/__init__.py
pulumi_lidarr/artists/artist.py
pulumi_lidarr/artists/get_artist.py
pulumi_lidarr/artists/get_artists.py
pulumi_lidarr/artists/outputs.py
pulumi_lidarr/config/__init__.py
pulumi_lidarr/config/vars.py
pulumi_lidarr/downloadclients/__init__.py
pulumi_lidarr/downloadclients/aria2.py
pulumi_lidarr/downloadclients/config.py
pulumi_lidarr/downloadclients/deluge.py
pulumi_lidarr/downloadclients/download_client.py
pulumi_lidarr/downloadclients/flood.py
pulumi_lidarr/downloadclients/get_config.py
pulumi_lidarr/downloadclients/get_download_client.py
pulumi_lidarr/downloadclients/get_download_clients.py
pulumi_lidarr/downloadclients/get_remote_path_mapping.py
pulumi_lidarr/downloadclients/get_remote_path_mappings.py
pulumi_lidarr/downloadclients/hadouken.py
pulumi_lidarr/downloadclients/nzbget.py
pulumi_lidarr/downloadclients/nzbvortex.py
pulumi_lidarr/downloadclients/outputs.py
pulumi_lidarr/downloadclients/pneumatic.py
pulumi_lidarr/downloadclients/qbittorrent.py
pulumi_lidarr/downloadclients/remote_path_mapping.py
pulumi_lidarr/downloadclients/rtorrent.py
pulumi_lidarr/downloadclients/sabnzbd.py
pulumi_lidarr/downloadclients/torrent_blackhole.py
pulumi_lidarr/downloadclients/torrent_download_station.py
pulumi_lidarr/downloadclients/transmission.py
pulumi_lidarr/downloadclients/usenet_blackhole.py
pulumi_lidarr/downloadclients/usenet_download_station.py
pulumi_lidarr/downloadclients/utorrent.py
pulumi_lidarr/downloadclients/vuze.py
pulumi_lidarr/importlists/__init__.py
pulumi_lidarr/importlists/exclusion.py
pulumi_lidarr/importlists/get_exclusion.py
pulumi_lidarr/importlists/get_exclusions.py
pulumi_lidarr/importlists/get_import_list.py
pulumi_lidarr/importlists/get_import_lists.py
pulumi_lidarr/importlists/headphones.py
pulumi_lidarr/importlists/import_list.py
