Metadata-Version: 2.1
Name: pulumi-lidarr
Version: 2.0.0a10
Summary: A Pulumi package for creating and managing Lidarr resources
Home-page: https://github.com/MaienM/pulumi-lidarr
License: Apache-2.0
Project-URL: Repository, https://github.com/MaienM/pulumi-lidarr
Keywords: pulumi lidarr category/utility
Requires-Python: >=3.7
